pyjjasim/__init__.py
pyjjasim/circuit_visualize.py
pyjjasim/embedded_graph.py
pyjjasim/josephson_circuit.py
pyjjasim/static_problem.py
pyjjasim/superlu_test.py
pyjjasim/time_evolution.py
pyjjasim/variable_row_array.py
pyjjasim/examples/__init__.py
pyjjasim/examples/daan_answer.py
pyjjasim/examples/readme_example.py
pyjjasim/examples/static_example1_single_vortex.py
pyjjasim/examples/static_example2_energy_barrier.py
pyjjasim/examples/static_example_0.py
pyjjasim/examples/static_example_1.py
pyjjasim/examples/static_example_10_custum_current_phase_relation.py
pyjjasim/examples/static_example_11_multithreading.py
pyjjasim/examples/static_example_2_single_vortex.py
pyjjasim/examples/static_example_3_inductance.py
pyjjasim/examples/static_example_4_parameter_optimization.py
pyjjasim/examples/static_example_5_lattices.py
pyjjasim/examples/static_example_6_array_with_hole.py
pyjjasim/examples/static_example_7_randomized_square_array.py
pyjjasim/examples/static_example_8_SQUID.py
pyjjasim/examples/static_example_9_custom_circuit.py
pyjjasim/examples/time_evolution_example_1_vortex_trains.py
pyjjasim/examples/time_evolution_example_2_IV_curve.py
pyjjasim/examples/time_evolution_example_3_current_pulse.py
pyjjasim/examples/time_evolution_example_4_hysterisis.py
pyjjasim/examples/time_evolution_example_5_giant_shapiro_steps.py
pyjjasim/examples/time_evolution_example_6_annealing.py
pyjjasim/examples/time_evolution_exaple_0.py
pyjjasim/tests/__init__.py
pyjjasim/tests/old_code.py
pyjjasim/tests/scrapbook.py
pyjjasim/tests/test_embedded_graph.py
pyjjasim/tests/test_josephson_junction_array.py
pyjjasim-4.0.2.dist-info/METADATA
pyjjasim-4.0.2.dist-info/WHEEL
pyjjasim-4.0.2.dist-info/top_level.txt
pyjjasim-4.0.2.dist-info/RECORD
