Metadata-Version: 2.1
Name: pyjjasim
Version: 4.0.2
Summary: Circuit Simulator including Josephson Junctions in Python
Home-page: UNKNOWN
Author: Martijn Lankhorst
Author-email: <m.lankhorst89@gmail.com>
License: UNKNOWN
Keywords: python,josephson_junction_array,circuit,simulation
Platform: UNKNOWN
Classifier: Development Status :: 5 - Production/Stable
Classifier: Programming Language :: Python :: 3
Classifier: Operating System :: Microsoft :: Windows
Requires-Dist: numpy
Requires-Dist: scipy
Requires-Dist: matplotlib
